LICENSE.txt
MANIFEST.in
README.rst
packages
requirements.txt
setup.py
callchain/__init__.py
callchain/call.py
callchain/chain.py
callchain/config.py
callchain/core.py
callchain/generic.py
callchain/keys.py
callchain/managers.py
callchain/patterns.py
callchain/settings.py
callchain/support.py
callchain.egg-info/PKG-INFO
callchain.egg-info/SOURCES.txt
callchain.egg-info/dependency_links.txt
callchain.egg-info/not-zip-safe
callchain.egg-info/requires.txt
callchain.egg-info/top_level.txt
callchain/active_auto/__init__.py
callchain/active_auto/chain.py
callchain/active_auto/chainlet.py
callchain/active_auto/event.py
callchain/active_auto/eventlet.py
callchain/active_man/__init__.py
callchain/active_man/chain.py
callchain/active_man/chainlet.py
callchain/active_man/event.py
callchain/active_man/eventlet.py
callchain/contrib/__init__.py
callchain/contrib/keys.py
callchain/contrib/logger.py
callchain/lazy_auto/__init__.py
callchain/lazy_auto/chain.py
callchain/lazy_auto/chainlet.py
callchain/lazy_auto/event.py
callchain/lazy_auto/eventlet.py
callchain/lazy_man/__init__.py
callchain/lazy_man/chain.py
callchain/lazy_man/chainlet.py
callchain/lazy_man/event.py
callchain/lazy_man/eventlet.py
callchain/services/__init__.py
callchain/services/apps.py
callchain/services/event.py
callchain/services/filter.py
callchain/services/map.py
callchain/services/order.py
callchain/services/queue.py
callchain/services/reduce.py
callchain/tests/__init__.py
callchain/tests/chain.py
callchain/tests/event.py
callchain/tests/manning.py
callchain/tests/test_active_chains.py
callchain/tests/test_active_events.py
callchain/tests/test_lazy_chains.py
callchain/tests/test_lazy_events.py
callchain/tests/auto/__init__.py
callchain/tests/auto/filtering.py
callchain/tests/auto/mapping.py
callchain/tests/auto/ordering.py
callchain/tests/auto/queuing.py
callchain/tests/auto/reducing.py
callchain/tests/man/__init__.py
callchain/tests/man/filtering.py
callchain/tests/man/manning.py
callchain/tests/man/mapping.py
callchain/tests/man/ordering.py
callchain/tests/man/queuing.py
callchain/tests/man/reducing.py