Metadata-Version: 1.0
Name: callchain
Version: 0.2.6
Summary: callables and components joined in one big happy chain
Home-page: https://bitbucket.org/lcrees/callchain
Author: L. C. Rees
Author-email: lcrees@gmail.com
License: BSD
Keywords: component architecture injection aspect-oriented appspace generator iterator functional
Platform: UNKNOWN
Classifier: Development Status :: 3 - Alpha
Classifier: Intended Audience :: Developers
Classifier: License :: OSI Approved :: BSD License
Classifier: Natural Language :: English
Classifier: Operating System :: OS Independent
Classifier: Programming Language :: Python
Classifier: Programming Language :: Python :: 2
Classifier: Programming Language :: Python :: 3
Classifier: Programming Language :: Python :: 2.6
Classifier: Programming Language :: Python :: 2.7
Classifier: Programming Language :: Python :: 3.2
Classifier: Programming Language :: Python :: Implementation :: CPython
Classifier: Topic :: Software Development
Classifier: Topic :: Software Development :: Libraries
Classifier: Topic :: Utilities
